[
  {
    "filename": "2. Małujowice koszorys sanitarny.pdf",
    "total_lines": 1030,
    "sections": [],
    "positions": [],
    "summary": {
      "NETTO": [
        "664 619,21\n"
      ],
      "BRUTTO": [
        "817 481,63\n"
      ]
    },
    "sample_lines": [
      "1: KLONEX II DŁUGI GRZEGORZ ul. Kasztanowa 10 49-318 Skarbimierz-",
      "2: Osiedle",
      "3: KOSZTORYS OFERTOWY - BRANŻA",
      "4: SANITARNA",
      "5: Klasyfikacja robót wg Wspólnego Słownika Zamówień",
      "6: 45200000-9 Roboty budowlane w zakresie wznoszenia kompletnych obiektów",
      "7: budowlanych lub ich części oraz roboty w zakresie inżynierii lądowej i",
      "8: wodnej",
      "9: 45111300-1 Roboty rozbiórkowe",
      "10: 45231300-8 Roboty budowlane w zakresie budowy wodociągów i rurociągów do",
      "11: odprowadzania ścieków",
      "12: 45332200-5 Roboty instalacyjne hydrauliczne",
      "13: 45332300-6 Roboty instalacyjne kanalizacyjne",
      "14: 45331100-7 Instalowanie centralnego ogrzewania",
      "15: 45331210-1 Instalowanie wentylacji",
      "16: 45331220-4 Instalowanie urządzeń klimatyzacyjnych",
      "17: NAZWA INWESTYCJI: BUDOWA DOMU LUDOWEGO",
      "18: ADRES INWESTYCJI: MAŁUJOWICE dz.nr 253 OBRĘB 0108 MAŁUJOWICE GMINA",
      "19: SKARBIMIERZ",
      "20: NAZWA INWESTORA: Gmina Skarbimierz",
      "21: ADRES INWESTORA: ul. Parkowa 12, 49-318 Skarbimierz Osiedle",
      "22: WYKONAWCA: KLONEX II DŁUGI GRZEGORZ",
      "23: ADRES WYKONAWCY: ul. KASZTANOWA 10, 49-318 Skarbimierz-Osiedle",
      "24: SPORZĄDZIŁ KALKULACJE",
      "25: Instalacje sanitarne",
      "26: DATA OPRACOWANIA: 12.2025",
      "27: Stawka roboczogodziny",
      "28: KOSZTORYS 35,00 zł",
      "29: Poz.: 27, 32, 33, 38 38,00 zł",
      "30: WARTOŚĆ KOSZTORYSOWA ROBÓT BEZ PODATKU VAT: 664 619,21 zł",
      "31: PODATEK VAT: (23%) 152 862,42 zł",
      "32: OGÓŁEM WARTOŚĆ KOSZTORYSOWA ROBÓT: 817 481,63 zł",
      "33: SŁOWNIE: osiemset siedemnaście tysięcy czterysta osiemdziesiąt jeden i 63/100 zł",
      "34: WYKONAWCA: INWESTOR:",
      "35: Data opracowania Data zatwierdzenia",
      "36: 12.2025",
      "37: Norma STANDARD - 365 Wersja: 5.17.100.8 Nr seryjny: 4539 Użytkownik: KLONEX II",
      "39: Norma STANDARD - 365 Wersja: 5.17.100.8 Nr seryjny: 4539 Użytkownik: KLONEX II",
      "40: Kosztorys ofertowy",
      "41: Lp. Podstawa Opis j.m. Ilość Cena Wartość",
      "42: KOSZTORYS:",
      "43: 1 ROBOTY ZEWNĘTRZNE",
      "44: 1.1 CPV PRZYŁĄCZA ZEWNĘTRZNE",
      "45: 45231300-8",
      "46: 1.1.1 CPV PRZYŁĄCZA KANALIZACJI SANITARNEJ",
      "47: 45231300-8",
      "48: 1.1.1. CPV ROBOTY ZIEMNE",
      "49: 1 45231300-8",
      "50: 1 KNNR 1 Roboty pomiarowe przy liniowych robotach ziemnych km 0,025 4 117,98 102,95",
      "51: d.1.1.1 0111-01 - trasa dróg w terenie równinnym.",
      "53: 2 KNR 2-01 Wykopy oraz przekopy wykonywane koparkami m3 (25 * 1,2 * 25,98 935,28",
      "54: d.1.1.1 0217-04 podsiębiernymi 0.25 m3 na odkład w gruncie kat. III - 1,5) * 0,8 =",
      "55: .1 80% 36,000",
      "56: 3 KNNR 1 Wykopy liniowe wykonane ręcznie -20% wykopów. m3 (25 * 1,2 * 81,28 731,52",
      "57: d.1.1.1 0307-01 1,5) * 0,2 =",
      "58: .1 9,000",
      "59: 4 KNNR 1 Zasypywanie wykopów o ścianach pionowych o m3 (25 * 1,2 * 54,19 2 438,55",
      "60: d.1.1.1 0318-01 szerokości 0.8-2.5 m i głęb.do 1.5 m w gr.kat. I-III 1,5) =",
      "61: .1 45,000",
      "62: 5 KNR 2-01 Zagęszczenie nasypów ubijakami mechanicznymi; m3 45,000 10,49 472,05",
      "63: d.1.1.1 0236-01 grunty sypkie kat. I-III",
      "65: Razem dział: ROBOTY ZIEMNE 4 680,35",
      "66: 1.1.1. CPV ROBOTY MONTAŻOWE",
      "67: 2 45231300-8",
      "68: 6 KNNR 4 Separator tłuszczu z osadnikiem fi1200 stud. 1,000 17 508,98 17 508,98",
      "69: d.1.1.1 1415-01",
      "71: 7 KNNR 4 Montaż z rur PVC łączonych na wcisk o śr. zewn. m 25,000 102,14 2 553,50",
      "72: d.1.1.1 1308-02 160 mm",
      "74: 8 KNNR 4 Studzienki kanalizacyjne systemowe o śr 315 mm - szt. 1,000 1 292,44 1 292,44",
      "75: d.1.1.1 1417-02 zamknięcie rurą teleskopową i włazem typu",
      "76: .2 ciężkiego.",
      "77: 9 KNR-W 2-18 Kształtki PVC kanalizacji zewnętrznej szt 4,000 115,66 462,64",
      "78: d.1.1.1 0421-03 jednokielichowe łączone na wcisk",
      "80: 10 KNR 2-18 Kanały rurowe - podłoża z materiałów sypkich o m2 25 * 1,2 = 36,31 1 089,30",
      "81: d.1.1.1 0501-02 grubości 15 cm 30,000",
      "83: 11 KNR 2-18 Próba szczelności kanałów rurowych o śr.nom. do m 25,000 28,81 720,25",
      "84: d.1.1.1 0804-02 200 mm.",
      "86: Razem dział: ROBOTY MONTAŻOWE 23 627,11",
      "87: Razem dział: PRZYŁĄCZA KANALIZACJI SANITARNEJ 28 307,46",
      "88: 1.1.2 CPV PRZYŁĄCZE WODY",
      "89: 45231300-8",
      "90: 1.1.2. CPV ROBOTY ZIEMNE",
      "91: 1 45231300-8",
      "92: 12 KNNR 1 Roboty pomiarowe przy liniowych robotach ziemnych km 0,025 4 117,98 102,95",
      "93: d.1.1.2 0111-01 - trasa dróg w terenie równinnym.",
      "95: 13 KNNR 1 Wykopy liniowe o szerokości 0,8-2,5 m i głębokości m3 (25 * 1,4 * 81,28 142,24",
      "96: d.1.1.2 0307-01 do 1,5 m o ścianach pionowych w gruntach suchych 1) * 0,05 =",
      "97: .1 kat. I-II -5% wykopów. 1,750",
      "98: 14 KNNR 1 Wykopy oraz przekopy o głęb.do 3.0 m wyk.na m3 (25 * 1,4 * 22,62 752,12",
      "99: d.1.1.2 0210-02 odkład koparkami podsiębiernymi o poj.łyżki 0.25 - 1) * 0,95 =",
      "100: .1 0.60 m3 w gr.kat. I-II. - 95% wykopów. 33,250"
    ],
    "knr_count": 190
  },
  {
    "filename": "3.KOSZTRYS OFERTOWY elektryczny.pdf",
    "total_lines": 208,
    "sections": [],
    "positions": [],
    "summary": {
      "NETTO": [
        "114 686,09\n"
      ],
      "BRUTTO": [
        "141 063,89\n"
      ]
    },
    "sample_lines": [
      "1: KLONEX II DŁUGI GRZEGORZ ul. Kasztanowa 10 49-318 Skarbimierz-",
      "2: Osiedle",
      "3: KOSZTORYS OFERTOWY - BRANŻA",
      "4: ELEKTRYCZNA",
      "5: NAZWA INWESTYCJI: Budowa budyku domu ludowego wraz z wiatą w miejscowości",
      "6: Małujowice na dz. nr 253",
      "7: ADRES INWESTYCJI: Małujowice dz. 253",
      "8: NAZWA INWESTORA: Gmina Skarbimierz",
      "9: ADRES INWESTORA: ul. Parkowa 12",
      "10: WYKONAWCA: KLONEX II DŁUGI GRZEGORZ",
      "11: ADRES WYKONAWCY: ul. KASZTANOWA 10, 49-318 Skarbimierz-Osiedle",
      "12: DATA OPRACOWANIA: 12.2025",
      "13: Stawka roboczogodziny",
      "14: KOSZTORYS 35,00 zł",
      "15: Poz.: 1 1 800,00 zł",
      "16: WARTOŚĆ KOSZTORYSOWA ROBÓT BEZ PODATKU VAT: 114 686,09 zł",
      "17: PODATEK VAT: (23%) 26 377,80 zł",
      "18: OGÓŁEM WARTOŚĆ KOSZTORYSOWA ROBÓT: 141 063,89 zł",
      "19: SŁOWNIE: sto czterdzieści jeden tysięcy sześćdziesiąt trzy i 89/100 zł",
      "20: WYKONAWCA: INWESTOR:",
      "21: Data opracowania Data zatwierdzenia",
      "22: 12.2025",
      "23: Norma STANDARD - 365 Wersja: 5.17.100.8 Nr seryjny: 4539 Użytkownik: KLONEX II",
      "24: BRANŻA ELEKTRYCZNA",
      "26: Norma STANDARD - 365 Wersja: 5.17.100.8 Nr seryjny: 4539 Użytkownik: KLONEX II",
      "27: BRANŻA ELEKTRYCZNA",
      "28: Kosztorys ofertowy",
      "29: Lp. Podstawa Opis j.m. Ilość Cena Wartość",
      "30: KOSZTORYS: BRANŻA ELEKTRYCZNA",
      "31: 1 LINIA KABLOWA I ROZDZIELNICA ELEKTRYZNA",
      "32: 1 Obsługa geodezyjna kpl 1,000 3 483,32 3 483,32",
      "33: d.1 wycena",
      "34: indywidualna",
      "35: 2 KNR-W 2-01 Wykopy liniowe o ścianach pionowych szerokości m3 (20 + 16) * 111,76 2 816,35",
      "36: d.1 0310-0201 0.8-1.5 m pod fundamenty, rurociągi, kolektory w 1 * 0,7 =",
      "37: gruntach suchych z wydobyciem urobku łopatą lub 25,200",
      "38: wyciągiem ręcznym kat. III-IV; głębokość do 1.5 m",
      "39: 3 KNR 5-10 Ręczne układanie kabli wielożyłowych o masie do m 20 + 16 = 29,62 1 066,32",
      "40: d.1 0103-02 1.0 kg/m na napięcie znamionowe poniżej 110 kV w 36,000",
      "41: rowach kablowych",
      "42: 4 KNR-W 2-01 Zasypywanie wykopów liniowych o ścianach m3 poz.2 = 82,63 2 082,28",
      "43: d.1 0312-0201 pionowych głębokości do 1.5 m i szerokości 0.8-1.5 25,200",
      "44: m; kat. gr. III-IV",
      "45: 5 KNNR 5 Montaż rozdzielnicy RG szt. 1,000 8 785,57 8 785,57",
      "46: d.1 0405-10",
      "47: 6 KNNR 5 Montaż certyfikowanego zestawu kpl. 1,000 7 764,99 7 764,99",
      "48: d.1 0401-01 Przeciwpożarowego Wyłącznika prądu 100A",
      "49: 7 KNNR 5 Montaż wyłącznika PWP szt. 1,000 318,26 318,26",
      "50: d.1 0406-02",
      "51: 8 KNR AL-01 Montaż zestawu - Lampka sygnalizacyjna PWP szt. 1,000 167,30 167,30",
      "52: d.1 0110-01",
      "53: 9 KNP 18 Pomiary rozdzielnic elektrycznych szt. 1,000 1 246,25 1 246,25",
      "54: d.1 1301-01.03",
      "55: 10 kalk. własna Pomiary obciążenia, dobór baterii kompensacji mocy kpl 1,000 6 000,00 6 000,00",
      "56: d.1 biernej",
      "57: Razem dział: LINIA KABLOWA I ROZDZIELNICA ELEKTRYZNA 33 730,64",
      "59: Norma STANDARD - 365 Wersja: 5.17.100.8 Nr seryjny: 4539 Użytkownik: KLONEX II",
      "60: BRANŻA ELEKTRYCZNA",
      "61: Kosztorys ofertowy",
      "62: Lp. Podstawa Opis j.m. Ilość Cena Wartość",
      "63: 2 Montaż opraw ośwetleniowych",
      "64: 11 KNNR 5 Montaż opraw oświetleniowych typ 1 kpl. 8,000 326,50 2 612,00",
      "65: d.2 0502-03",
      "66: 12 KNNR 5 Montaż opraw oświetleniowych typ 2 kpl. 21,000 357,21 7 501,41",
      "67: d.2 0502-03",
      "68: 13 KNNR 5 Oprawy oświetleniowe w sufitach podwieszanych - kpl. 22,000 372,79 8 201,38",
      "69: d.2 0503-02 świetlówkowa do 3x40 W",
      "70: 14 KNNR 5 Montaż opraw oświetleniowych typ 4 kpl. 10,000 326,50 3 265,00",
      "71: d.2 0502-03",
      "72: 15 KNNR 5 Oprawy oświetleniowe w sufitach podwieszanych - kpl. 4,000 380,47 1 521,88",
      "73: d.2 0503-02 świetlówkowa do 3x40 W",
      "74: 16 KNNR 5 Montaż opraw awaryjnych kierunkowych AW kpl. 16,000 318,38 5 094,08",
      "75: d.2 0502-02",
      "76: 17 KNNR 5 Montaż opraw Z1 kpl. 6,000 272,31 1 633,86",
      "77: d.2 0502-02",
      "78: 18 KNNR 5 Montaż opraw Z2 kpl. 2,000 272,31 544,62",
      "79: d.2 0502-02",
      "80: Razem dział: Montaż opraw ośwetleniowych 30 374,23",
      "82: Norma STANDARD - 365 Wersja: 5.17.100.8 Nr seryjny: 4539 Użytkownik: KLONEX II",
      "83: BRANŻA ELEKTRYCZNA",
      "84: Kosztorys ofertowy",
      "85: Lp. Podstawa Opis j.m. Ilość Cena Wartość",
      "86: 3 Osprzęt elektroinstalacyjny",
      "87: 19 KNNR 5 Przygotowanie podłoża pod osprzęt instalacyjny szt. 410,000 2,14 877,40",
      "88: d.3 0301-14 mocowany przez przykręcenie - wykonanie otworów",
      "89: w blasze",
      "90: 20 KNNR 5 Przebijanie otworów śr. 25 mm o długości do 40 cm otw. 40,000 126,66 5 066,40",
      "91: d.3 1209-1201 w ścianach lub stropach z betonu",
      "92: 21 KNNR 5 Puszki instalacyjne podtynkowe pojedyncze o śr.do szt. 15,000 6,59 98,85",
      "93: d.3 0302-01 60 mm",
      "94: 22 KNNR 5 Puszki z tworzywa sztucznego o wym. 75x75 mm o 4 szt. 37,000 35,56 1 315,72",
      "95: d.3 0303-02 wylotach dla przewodów o przekroju do 2.5 mm2",
      "96: 23 KNNR 5 Łączniki i przyciski jednobiegunowe podtynkowe w szt. 3,000 29,50 88,50",
      "97: d.3 0306-02 puszce instalacyjnej",
      "98: 24 KNNR 5 Łączniki świecznikowe podtynkowe w puszce szt. 1,000 31,60 31,60",
      "99: d.3 0306-03 instalacyjnej",
      "100: 25 KNNR 5 Łączniki krzyżowe, dwubiegunowe podtynkowe w szt. 2,000 34,45 68,90"
    ],
    "knr_count": 6
  },
  {
    "filename": "2. SIECIEBOROWICE KOSZTORYS SANITARNY.pdf",
    "total_lines": 5619,
    "sections": [],
    "positions": [],
    "summary": {
      "RAZEM": [
        "410 946,64 129 651,74 272 504,57 8 790,33\n",
        "424 790,95 142 617,00 272 504,57 9 669,38\n",
        "444 790,95 20 000,00 142 617,00 272 504,57 9 669,38\n"
      ],
      "NETTO": [
        "20 81 272 5 493,96 51 13 444 790,95 81,30"
      ],
      "BRUTTO": [
        "547 092,87 100,00"
      ],
      "OGÓŁEM": [
        "547 092,87\n"
      ]
    },
    "sample_lines": [
      "1: KLONEX II DŁUGI GRZEGORZ ul. KASZTANOWA 10 49-318",
      "2: SKARBIMIERZ - OSIEDLE",
      "3: KOSZTORYS OFERTOWY - BRANŻA",
      "4: SANITARNA",
      "5: NAZWA INWESTYCJI: BUDOWA ŚWIETLICY WIEJSKIEJ W SIECIEBOROWICACH",
      "6: ADRES INWESTYCJI: SIECIEBOROWICE dz.nr 46 OBRĘB SIECIEBOROWICE GMINA",
      "8: NAZWA INWESTORA: URZĄD GMINY OŁAWA",
      "9: ADRES INWESTORA: ul. PIŁSUDSKIEGO 28, 55-200 OŁAWA",
      "10: WYKONAWCA: KLONEX II DŁUGI GRZEGORZ",
      "11: ADRES WYKONAWCY: ul. KASZTANOWA 10, 49-318 Skarbimierz-Osiedle",
      "12: SPORZĄDZIŁ KALKULACJE",
      "13: Instalacje sanitarne mgr inż. Piotr Piotrowski",
      "14: DATA OPRACOWANIA: 12.2024",
      "15: Stawka roboczogodziny 28,00 zł",
      "16: WARTOŚĆ KOSZTORYSOWA ROBÓT BEZ PODATKU VAT: 444 790,95 zł",
      "17: PODATEK VAT: (23%) 102 301,92 zł",
      "18: OGÓŁEM WARTOŚĆ KOSZTORYSOWA ROBÓT: 547 092,87 zł",
      "19: SŁOWNIE: pięćset czterdzieści siedem tysięcy dziewięćdziesiąt dwa i 87/100 zł",
      "20: WYKONAWCA: INWESTOR:",
      "21: Data opracowania Data zatwierdzenia",
      "22: 12.2024",
      "23: Norma STANDARD - 365 Wersja: 5.16.200.16 Nr seryjny: 4250 Użytkownik: 147A-FBF0-D132-079E-E623",
      "24: Tabela elementów scalonych",
      "25: Uproszcz Robocizn",
      "26: Lp. Nazwa Materiały Sprzęt Kp Z Razem Udział %",
      "28: 1 ROBOTY 0,00 53 204 2 907,80 34 9 084,27 304 193,57 55,60%",
      "29: WEWNĘTRZNE 868,36 267,42 065,72",
      "30: 1.1 INSTALACJA 0,00 8 498,74 4 102,98 245,08 5 246,29 1 399,02 19 492,11 3,56%",
      "31: KANALIZACJI",
      "32: SANITARNEJ",
      "33: PODPOSADZKOWEJ",
      "34: W BUDYNKU",
      "35: 1.1.1 Roboty ziemne 0,00 7 001,24 841,41 55,25 4 233,90 1 129,04 13 260,84 2,42%",
      "36: instalacji kanalizacji",
      "37: sanitarnej",
      "38: 1.1.2 Roboty montażowe 0,00 1 497,50 3 261,57 189,83 1 012,39 269,98 6 231,27 1,14%",
      "39: instalacja kanalizacji",
      "40: sanitarnej",
      "41: 1.2 INSTALACJA 0,00 6 336,32 41 19,80 3 813,69 1 016,99 52 262,51 9,55%",
      "42: KANALIZACJI 075,71",
      "43: SANITARNEJ",
      "44: NADDPOSADZKOWE",
      "45: J W BUDYNKU",
      "46: 1.2.1 POZIOMY 0,00 3 303,79 4 529,93 0,41 1 982,54 528,69 10 345,36 1,89%",
      "47: 1.2.2 ARMAURA I BIAŁY 0,00 3 032,53 36 19,39 1 831,15 488,30 41 917,15 7,66%",
      "48: MONTAŻ 545,78",
      "49: 1.2.2.1 ARMATURA I BIAŁY 0,00 2 654,53 30 19,39 1 604,35 427,82 35 487,97 6,49%",
      "50: MONTAŻ 781,88",
      "51: 1.2.2.2 WYPOSAŻENIE 0,00 378,00 5 763,90 0,00 226,80 60,48 6 429,18 1,18%",
      "52: ŁAZIENEK DLA",
      "53: NIEPEŁNOSPRAWNY",
      "55: 1.3 INSTALACJA WODY 0,00 6 206,41 16 355,73 3 937,29 1 049,99 27 814,25 5,08%",
      "56: ZIMNEJ , C.W.U, 264,83",
      "57: HYDRANTOWEJ",
      "58: 1.3.1 INSTALACJA WODY 0,00 6 206,41 16 355,73 3 937,29 1 049,99 27 814,25 5,08%",
      "59: ZIMNEJ , C.W.U, 264,83",
      "60: HYDRANTOWEJ",
      "61: 1.3.1.1 Roboty montażowe 0,00 6 016,49 16 281,16 3 778,60 1 007,67 27 348,75 5,00%",
      "62: instalacji zimnej i 264,83",
      "63: ciepłej wody",
      "64: 1.3.1.2 UTYLIZACJA 0,00 189,92 0,00 74,57 158,69 42,32 465,50 0,09%",
      "65: ODPADÓW",
      "66: 1.4 INSTALACJA 0,00 8 295,16 27 140,77 5 061,57 1 349,75 42 718,08 7,81%",
      "67: WEWNĘTRZNA 870,83",
      "68: CENTRALNEGO",
      "69: GRZEWANIA",
      "70: 1.4.1 1. Ogrzewanie 0,00 5 661,89 26 112,80 3 464,83 923,96 36 532,12 6,68%",
      "71: podłogowe 368,64",
      "72: 1.4.2 D.III.1 Roboty 0,00 1 382,08 40,39 2,78 830,92 221,57 2 477,74 0,45%",
      "73: montażowe instalacji",
      "75: 1.4.3 D.III.2 Roboty 0,00 460,32 0,00 0,00 276,19 73,65 810,16 0,15%",
      "76: budowlane instalacji",
      "78: 1.4.4 D.III.3 Roboty 0,00 790,87 1 461,80 25,19 489,63 130,57 2 898,06 0,53%",
      "79: izolacyjne c.o.",
      "80: 1.5 WENTYLACJA 0,00 24 114 2 146,42 16 4 268,52 161 906,62 29,59%",
      "81: MECHANICZNA Z 531,73 953,07 006,88",
      "82: REKUPERACJĄ",
      "83: 1.5.1 UKŁAD WENTYLACJI 0,00 6 445,84 27 536,69 4 189,52 1 117,20 39 389,99 7,20%",
      "84: MECHANICZNEJ CW1 100,74",
      "85: 1.5.1.1 ROBOTY 0,00 4 380,78 25 470,55 2 910,81 776,21 33 832,07 6,18%",
      "86: MONTAŻOWE UKŁAD 293,72",
      "88: 1.5.1.2 Roboty izoloacyjne 0,00 640,05 1 467,04 62,15 421,32 112,35 2 702,91 0,49%",
      "89: układu CW1",
      "90: 1.5.1.3 Roboty budowlane 0,00 1 425,01 339,98 3,99 857,39 228,64 2 855,01 0,52%",
      "91: towarzyszące",
      "93: Norma STANDARD - 365 Wersja: 5.16.200.16 Nr seryjny: 4250 Użytkownik: 147A-FBF0-D132-079E-E623",
      "94: Tabela elementów scalonych",
      "95: Uproszcz Robocizn",
      "96: Lp. Nazwa Materiały Sprzęt Kp Z Razem Udział %",
      "98: 1.5.2 UKŁAD WENTYLACJI 0,00 7 578,08 43 773,24 5 010,81 1 336,22 58 664,79 10,72%",
      "99: MECHANICZNEJ CW2 966,44",
      "100: 1.5.2.1 ROBOTY 0,00 5 224,06 41 679,04 3 541,88 944,51 51 886,59 9,48%"
    ],
    "knr_count": 177
  },
  {
    "filename": "1. SIECIEBOROWICE BUDOWLANY DOPASOWA.pdf",
    "total_lines": 2793,
    "sections": [],
    "positions": [],
    "summary": {
      "RAZEM": [
        "54 416,46\n2 ",
        "78 251,78 43 26 883,20 7 893,95\n474,63\n3 ",
        "96 112,70 57 38 689,35 314,96\n108,39\n4 "
      ],
      "NETTO": [
        "147 255 337 10 159 42 954 040,66 81,30"
      ],
      "BRUTTO": [
        "1 173 470,01 100,00"
      ],
      "OGÓŁEM": [
        "1 173 470,01\n"
      ]
    },
    "sample_lines": [
      "1: KOSZTORYS INWESTORSKI",
      "2: NAZWA INWESTYCJI: Budowa budynku przedszkola w Skarbimierzu Osiedle - Roboty",
      "3: budowlane inwestycyjne",
      "4: ADRES INWESTYCJI: Skarbimierz Osiedle, ul. Akacjowa, dz. nr 49",
      "5: NAZWA INWESTORA: Gmina Skarbimierz",
      "6: ADRES INWESTORA: Skarbimierz Osiedle, ul. Parkowa 12",
      "7: BRANŻE: budowlana",
      "8: SPORZĄDZIŁ KALKULACJE",
      "9: mgr inż. Robert Łukiewicz",
      "10: DATA OPRACOWANIA: 20.12.2018",
      "11: Stawka roboczogodziny",
      "12: KOSZTORYS 28,00 zł",
      "13: Poz.: 99 5 000,00 zł",
      "14: Poz.: 71, 72, 73, 74, 75, 32,00 zł",
      "15: 76, 77, 78",
      "16: WARTOŚĆ KOSZTORYSOWA ROBÓT BEZ PODATKU VAT: 954 040,66 zł",
      "17: PODATEK VAT: (23%) 219 429,35 zł",
      "18: OGÓŁEM WARTOŚĆ KOSZTORYSOWA ROBÓT: 1 173 470,01 zł",
      "19: SŁOWNIE: jeden milion sto siedemdziesiąt trzy tysiące czterysta siedemdziesiąt i",
      "20: 1/100 zł",
      "21: WYKONAWCA: INWESTOR:",
      "22: Data opracowania Data zatwierdzenia",
      "23: 20.12.2018",
      "24: Norma STANDARD - 365 Wersja: 5.16.200.16 Nr seryjny: 4250 Użytkownik: 147A-FBF0-D132-079E-E623",
      "25: Tabela elementów scalonych",
      "26: Uproszcz Robocizn",
      "27: Lp. Nazwa Materiały Sprzęt Kp Z Razem Udział %",
      "29: 1 PRACE 54 0,00 0,00 0,00 0,00 0,00 54 416,46 4,64%",
      "30: PROJEKTOWE, 416,46",
      "31: UZGONIENIA, OPINIE",
      "32: ORGANIZACJA",
      "33: PLACU BUDOWY",
      "34: 2 Roboty ziemne i 0,00 24 26 4 485,34 17 4 669,66 78 251,78 6,67%",
      "35: fundamentowe 701,52 883,20 512,06",
      "36: 3 Posadzki 0,00 32 38 178,78 19 5 220,53 96 112,70 8,19%",
      "37: 448,00 689,35 576,04",
      "38: 4 Roboty murowe i 0,00 18 38 19,20 11 2 976,24 71 647,04 6,11%",
      "39: ścianki działowe 582,61 907,89 161,10",
      "40: 5 Roboty betonowe 0,00 3 390,43 3 645,68 298,66 2 213,67 589,85 10 138,29 0,86%",
      "41: 6 Tynki, okładziny i 0,00 50 79 1 620,34 31 8 355,09 171 585,59 14,62%",
      "42: roboty malarskie 601,25 676,02 332,89",
      "43: 7 Okna, drzwi, parapety 0,00 3 885,70 54 81,38 2 380,21 634,77 61 717,52 5,26%",
      "44: wewnętrzne 735,46",
      "45: 8 Dach, pokrycie 46 31 43 530,90 19 5 173,91 146 887,29 12,52%",
      "46: dachowe, rynny, rury 099,20 802,52 881,02 399,74",
      "47: spustowe, wyłaz na",
      "49: 9 Elewacja i prace 0,00 49 14 686,11 29 7 961,69 101 779,29 8,67%",
      "50: wykończeniowe 073,54 202,20 855,75",
      "51: 10 Zagospodarowanie 0,00 32 37 1 296,78 19 5 332,41 95 929,99 8,17%",
      "52: terenu 031,65 272,96 996,19",
      "53: 11 Rusztowanie 0,00 3 700,50 99,74 1 588,07 3 173,02 846,48 9 407,81 0,80%",
      "54: 12 Obsługa geodezyjna 0,00 5 000,00 0,00 0,00 3 000,00 800,00 8 800,00 0,75%",
      "55: 13 WYPOSAŻENIE 47 0,00 0,00 0,00 0,00 0,00 47 366,90 4,04%",
      "56: KUCHNI I ZAPLECZA 366,90",
      "57: KUCHENNEGO",
      "58: Kosztorys netto 147 255 337 10 159 42 954 040,66 81,30%",
      "59: 882,56 217,72 993,52 785,56 600,67 560,63",
      "60: VAT 23% 219 429,35 18,70%",
      "61: Kosztorys brutto 1 173 470,01 100,00%",
      "62: Słownie: jeden milion sto siedemdziesiąt trzy tysiące czterysta siedemdziesiąt i 1/100 zł",
      "64: Norma STANDARD - 365 Wersja: 5.16.200.16 Nr seryjny: 4250 Użytkownik: 147A-FBF0-D132-079E-E623",
      "65: Kosztorys",
      "67: Lp. Podstawa Opis j.m. Nakłady R M S",
      "69: KOSZTORYS:",
      "70: 1 PRACE PROJEKTOWE, UZGONIENIA, OPINIE ORGANIZACJA PLACU BUDOWY",
      "71: 1 PRACE PROJEKTOWE 1,000 0,000",
      "73: obmiar = 1,000",
      "74: Razem z narzutami 54 416,46 54 416,4",
      "76: Cena jednostkowa 54 416,460",
      "77: Razem dział: PRACE PROJEKTOWE, UZGONIENIA,",
      "78: OPINIE ORGANIZACJA PLACU BUDOWY",
      "79: Razem koszty bezpośrednie: 0,00",
      "80: RAZEM: 54 416,46",
      "81: 2 Roboty ziemne i fundamentowe",
      "82: 2 KNR 2-01 Usunięcie warstwy ziemi m2 409,886 0,272",
      "83: d.2 0126-01 urodzajnej (humusu) o grubości",
      "84: do 15 cm za pomocą spycharek",
      "85: obmiar = 409,886 m2",
      "86: -- R --",
      "87: 1* robocizna r-g 2,1531 0,147 60,25",
      "88: 0,0055 * 0,955 = 0,005253 r-g/m2",
      "89: * 28,00 zł/r-g",
      "90: -- S --",
      "91: 2* spycharka gąsienicowa 74 kW m-g 1,0247 0,125 51,24",
      "92: (100 KM)",
      "93: 0,0025 m-g/m2 * 50,00 zł/m-g",
      "94: Razem koszty bezpośrednie 111,49 0,272 60,25 51,24",
      "95: Jednostkowe koszty bezpośrednie 0,272 0,147 0,125",
      "96: Razem z narzutami 196,34 0,479 106,16 90,18",
      "97: Cena jednostkowa 0,479 0,259 0,220",
      "98: 3 KNR 2-01 Usunięcie warstwy ziemi m2 409,886 0,272",
      "99: d.2 0126-02 urodzajnej (humusu) za pomocą",
      "100: spycharek - dodatek za każde"
    ],
    "knr_count": 84
  },
  {
    "filename": "3. SIECIEBOROWICE KOSZTORYS ELEKTRYCZNY.pdf",
    "total_lines": 1878,
    "sections": [],
    "positions": [],
    "summary": {
      "RAZEM": [
        "470,65 162,96 304,70 2,99\n1.1.2 45311000",
        "335,43 201,83 122,65 10,95\n1.1.3 45317300",
        "11 725,22 243,47 11 481,75\n1.1.4 45310000"
      ],
      "NETTO": [
        "486,00 24 110 417,45 15 4 040,72 155 924,49 81,30"
      ],
      "BRUTTO": [
        "191 787,12 100,00"
      ],
      "OGÓŁEM": [
        "191 787,12\n"
      ]
    },
    "sample_lines": [
      "1: KLONEX II DŁUGI GRZEGORZ ul. KASZTANOWA 10 49-318",
      "2: SKARBIMIERZ - OSIEDLE",
      "3: KOSZTORYS OFERTOWY - BRANŻA",
      "4: ELEKTRYCZNA",
      "5: NAZWA INWESTYCJI: BUDOWA ŚWIETLICY WIEJSKIEJ W MIEJSCOWOŚCI",
      "6: SIECIEBOROWICE",
      "7: ADRES INWESTYCJI: SIECIEBOROWICE DZ NR 46 GMINA OŁAWA",
      "8: NAZWA INWESTORA: GMINA OŁAWA",
      "9: ADRES INWESTORA: PL. MARSZAŁKA J. PIŁSUDSKIEGO 28, 55-200 OŁAWA",
      "10: WYKONAWCA: KLONEX II DŁUGI GRZEGORZ",
      "11: ADRES WYKONAWCY: ul. KASZTANOWA 10, 49-318 Skarbimierz-Osiedle",
      "12: BRANŻE: Elektryczna",
      "13: DATA OPRACOWANIA: 2025-01-10",
      "14: Stawka roboczogodziny 29,00 zł",
      "15: WARTOŚĆ KOSZTORYSOWA ROBÓT BEZ PODATKU VAT: 155 924,49 zł",
      "16: PODATEK VAT: (23%) 35 862,63 zł",
      "17: OGÓŁEM WARTOŚĆ KOSZTORYSOWA ROBÓT: 191 787,12 zł",
      "18: SŁOWNIE: sto dziewięćdziesiąt jeden tysięcy siedemset osiemdziesiąt siedem i",
      "19: 12/100 zł",
      "20: WYKONAWCA: INWESTOR:",
      "21: Data opracowania Data zatwierdzenia",
      "22: 2025-01-10",
      "23: Norma STANDARD - 365 Wersja: 5.16.200.16 Nr seryjny: 4250 Użytkownik: 147A-FBF0-D132-079E-E623",
      "24: PRZEDMIAR:",
      "25: Tabela elementów scalonych",
      "26: Uproszcz Robocizn",
      "27: Lp. Nazwa Materiały Sprzęt Kp Z Razem Udział %",
      "29: 1 INSTALACJE 486,00 24 110 417,45 15 4 040,72 155 924,49 81,30%",
      "30: ELEKTRYCZNE 873,02 927,67 179,63",
      "31: 1.1 Wewnętrzna instalacja 486,00 15 43 29,66 9 586,78 2 549,82 71 801,00 37,44%",
      "32: elektryczna 939,14 209,60",
      "33: 1.1.1 Instalacja uziemienia i 0,00 92,57 304,70 1,69 56,59 15,10 470,65 0,25%",
      "34: wyrównawcza",
      "35: 1.1.2 Linie zasilające 0,00 114,64 122,65 6,22 72,57 19,35 335,43 0,17%",
      "36: 1.1.3 Rozdzielnie 0,00 138,33 11 0,00 83,00 22,14 11 725,22 6,11%",
      "37: 481,75",
      "38: 1.1.4 Montaż instalacji opraw 0,00 6 726,97 19 0,00 4 038,10 1 074,25 31 565,74 16,46%",
      "39: oświetlenia 726,42",
      "40: podstawowego i",
      "41: awaryjo-ewakuacyjneg",
      "43: 1.1.5 Instalacja gniazd i 0,00 3 982,33 8 521,16 0,00 2 392,94 634,72 15 531,15 8,10%",
      "44: obwodów 230/400V",
      "45: 1.1.6 Instalacja odgromowa 0,00 2 862,42 3 052,92 21,75 1 730,40 460,95 8 128,44 4,24%",
      "46: 1.1.7 Pomiary elektryczne 486,00 2 021,88 0,00 0,00 1 213,18 323,31 4 044,37 2,11%",
      "47: 1.2 Zewnętrzna instalacja 0,00 8 933,88 67 387,79 5 592,85 1 490,90 84 123,49 43,86%",
      "48: elektryczna 718,07",
      "49: 1.2.1 Linie zasilające 0,00 4 793,79 3 017,09 149,81 2 966,79 790,52 11 718,00 6,11%",
      "50: 1.2.2 Instalacja uziemienia i 0,00 523,14 806,40 41,76 338,30 90,64 1 800,24 0,94%",
      "51: wyrównawcza",
      "52: 1.2.3 Oświetlenie 0,00 1 362,49 11 196,22 935,19 249,04 14 662,52 7,65%",
      "53: zewnętrzne 919,58",
      "54: 1.2.4 Pomiary elektryczne 0,00 2 254,46 0,00 0,00 1 352,57 360,70 3 967,73 2,07%",
      "55: 1.2.5 Instalacja 0,00 0,00 51 0,00 0,00 0,00 51 975,00 27,10%",
      "56: fotowoltaiczna 975,00",
      "57: Kosztorys netto 486,00 24 110 417,45 15 4 040,72 155 924,49 81,30%",
      "58: 873,02 927,67 179,63",
      "59: VAT 23% 35 862,63 18,70%",
      "60: Kosztorys brutto 191 787,12 100,00%",
      "61: Słownie: sto dziewięćdziesiąt jeden tysięcy siedemset osiemdziesiąt siedem i 12/100 zł",
      "63: Norma STANDARD - 365 Wersja: 5.16.200.16 Nr seryjny: 4250 Użytkownik: 147A-FBF0-D132-079E-E623",
      "64: PRZEDMIAR:",
      "65: Kosztorys",
      "67: Lp. Podstawa Opis j.m. Nakłady R M S",
      "69: KOSZTORYS: PRZEDMIAR:",
      "70: 1 INSTALACJE ELEKTRYCZNE",
      "71: 1.1 Wewnętrzna instalacja elektryczna",
      "72: 1.1.1 45310000-3 Instalacja uziemienia i wyrównawcza",
      "73: 1 KNNR 5 Przewody uziemiające i m 5,000 20,14",
      "74: d.1.1. 0602-02 wyrównawcze w budynkach",
      "75: 1 mocowane na wspornikach",
      "76: ściennych na podłożu innym niż",
      "77: drewno - bednarka ocynkowana",
      "78: FeZn 25x4mm",
      "79: obmiar = 5,000 m",
      "80: -- R --",
      "81: 1* robocizna r-g 1,7200 9,98 49,90",
      "82: 0,344 r-g/m * 29,00 zł/r-g",
      "83: -- M --",
      "84: 2* bednarka ocynkowana' m 5,2000 4,92 24,60",
      "85: 1,04 m/m * 4,73 zł/m",
      "86: 3* wsporniki ścienne szt. 5,0500 4,78 23,90",
      "87: 1,01 szt./m * 4,73 zł/szt.",
      "88: 4* śruby stalowe z nakrętkami i kg 0,0300 0,09 0,45",
      "89: podkładkami",
      "90: 0,006 kg/m * 14,18 zł/kg",
      "91: 5* materiały pomocnicze(od M) % 0,24 1,20",
      "93: -- S --",
      "94: 6* spawarka m-g 0,1470 0,13 0,65",
      "95: 0,0294 m-g/m * 4,50 zł/m-g",
      "96: Razem koszty bezpośrednie 100,70 20,14 49,90 50,15 0,65",
      "97: Jednostkowe koszty bezpośrednie 20,14 9,98 10,03 0,13",
      "98: Razem z narzutami 139,15 27,83 87,85 50,15 1,15",
      "99: Cena jednostkowa 27,83 17,57 10,03 0,23",
      "100: 2 KNNR 5 Montaż głównej szyny szt. 1,000 160,02"
    ],
    "knr_count": 5
  }
]